setup.py
ergondata_executions/__init__.py
ergondata_executions/interfaces.py
ergondata_executions.egg-info/PKG-INFO
ergondata_executions.egg-info/SOURCES.txt
ergondata_executions.egg-info/dependency_links.txt
ergondata_executions.egg-info/requires.txt
ergondata_executions.egg-info/top_level.txt
ergondata_executions/v1/__init__.py
ergondata_executions/v1/api_exceptions.py
ergondata_executions/v1/api_logger.py
ergondata_executions/v1/client.py
ergondata_executions/v1/decorators.py
ergondata_executions/v1/helpers.py
ergondata_executions/v1/auth/__init__.py
ergondata_executions/v1/auth/controller.py
ergondata_executions/v1/auth/interfaces.py
ergondata_executions/v1/process/__init__.py
ergondata_executions/v1/process/controller.py
ergondata_executions/v1/process/interfaces.py
ergondata_executions/v1/queue/__init__.py
ergondata_executions/v1/queue/controller.py
ergondata_executions/v1/queue/interfaces.py
ergondata_executions/v1/queue_event_subscription/__init__.py
ergondata_executions/v1/queue_event_subscription/controller.py
ergondata_executions/v1/queue_event_subscription/interfaces.py
ergondata_executions/v1/queue_exception/__init__.py
ergondata_executions/v1/queue_exception/controller.py
ergondata_executions/v1/queue_exception/interfaces.py
ergondata_executions/v1/queue_item/__init__.py
ergondata_executions/v1/queue_item/controller.py
ergondata_executions/v1/queue_item/interfaces.py
ergondata_executions/v1/queue_priority/__init__.py
ergondata_executions/v1/queue_priority/controller.py
ergondata_executions/v1/queue_priority/interfaces.py
ergondata_executions/v1/task/__init__.py
ergondata_executions/v1/task/controller.py
ergondata_executions/v1/task/interfaces.py
ergondata_executions/v1/task_event_subscription/__init__.py
ergondata_executions/v1/task_event_subscription/controller.py
ergondata_executions/v1/task_event_subscription/interfaces.py
ergondata_executions/v1/task_exception/__init__.py
ergondata_executions/v1/task_exception/controller.py
ergondata_executions/v1/task_exception/interfaces.py
ergondata_executions/v1/task_execution/__init__.py
ergondata_executions/v1/task_execution/controller.py
ergondata_executions/v1/task_execution/interfaces.py
