Metadata-Version: 2.1
Name: ergondata-executions
Version: 1.4.6
Summary: Collection of methods to connect and interact with Ergondata's Execution API
Home-page: UNKNOWN
Author: Daniel Anzanello Vossos
Author-email: daniel.vossos@ergondata.com.br
License: MIT
Keywords: executions
Platform: UNKNOWN
